{
  "kind": "collectionType",
  "collectionName": "blogs",
  "info": {
    "singularName": "blog",
    "pluralName": "blogs",
    "displayName": "Blog",
    "description": ""
  },
  "options": {
    "draftAndPublish": false
  },
  "pluginOptions": {},
  "attributes": {
    "product": {
      "type": "relation",
      "relation": "oneToOne",
      "target": "api::product.product",
      "private": true
    },
    "preview": {
      "displayName": "Blog",
      "type": "component",
      "repeatable": false,
      "component": "media.blog",
      "required": false
    },
    "content": {
      "type": "component",
      "repeatable": false,
      "component": "media.blog",
      "required": true
    }
  }
}
